pylax/__init__.py
pylax/cli.py
pylax-0.1.0.dist-info/licenses/LICENSE
pylax-0.1.0.dist-info/METADATA
pylax-0.1.0.dist-info/WHEEL
pylax-0.1.0.dist-info/entry_points.txt
pylax-0.1.0.dist-info/top_level.txt
pylax-0.1.0.dist-info/RECORD
