Metadata-Version: 2.4
Name: pylax
Version: 0.1.0
Summary: Zero-friction Python environment orchestrator. Never activate again.
Author-email: Nuhman PK <nuhmanpk7@gmail.com>
Project-URL: Homepage, https://github.com/nuhmanpk/pylax
Project-URL: Bug Tracker, https://github.com/nuhmanpk/pylax/issues
Classifier: Programming Language :: Python :: 3
Classifier: License :: OSI Approved :: MIT License
Classifier: Operating System :: OS Independent
Requires-Python: >=3.7
License-File: LICENSE
Provides-Extra: test
Requires-Dist: pytest; extra == "test"
Dynamic: license-file
